configfile.py
py_configfile-0.0.4.dist-info/LICENSE
py_configfile-0.0.4.dist-info/METADATA
py_configfile-0.0.4.dist-info/WHEEL
py_configfile-0.0.4.dist-info/top_level.txt
py_configfile-0.0.4.dist-info/RECORD
